scrapy_html/__init__.py
scrapy_html/scraper.py
scrapy_html/validators.py
scrapy_html-1.4.1.dist-info/licenses/LICENSE
scrapy_html-1.4.1.dist-info/METADATA
scrapy_html-1.4.1.dist-info/WHEEL
scrapy_html-1.4.1.dist-info/entry_points.txt
scrapy_html-1.4.1.dist-info/top_level.txt
scrapy_html-1.4.1.dist-info/RECORD
