Metadata-Version: 2.4
Name: scrapy_html
Version: 1.4.1
Summary: 🌐 Um scraper que retorna o HTML completo de uma URL, tags, classes e atributos usando BeautifulSoup
Home-page: https://github.com/robertolima-dev/scrapy-html
Author: Roberto Lima
Author-email: Roberto Lima <robertolima.izphera@gmail.com>
License-Expression: MIT
Project-URL: Homepage, https://github.com/robertolima-dev/scrapy-html
Project-URL: Repository, https://github.com/robertolima-dev/scrapy-html
Project-URL: Issues, https://github.com/robertolima-dev/scrapy-html/issues
Classifier: Programming Language :: Python :: 3
Classifier: Operating System :: OS Independent
Requires-Python: >=3.6
License-File: LICENSE
Requires-Dist: beautifulsoup4>=4.12.0
Requires-Dist: requests>=2.31.0
Requires-Dist: lxml>=4.9.0
Provides-Extra: lxml
Requires-Dist: lxml>=4.9.0; extra == "lxml"
Provides-Extra: html5lib
Requires-Dist: html5lib>=1.1; extra == "html5lib"
Dynamic: author
Dynamic: home-page
Dynamic: license-file
Dynamic: requires-python
